{
	"_comment": "Custom card images for achievement CATEGORIES (the grouped /achievements page cards + homepage). One row per category. `type` is the hr title string — the SAME value Achievement rows stack on in /achievements/summary — so the route looks up a category's image by the group title it already computes. A group with no matching category row falls back to the stock medal/record icon. imageUrl/imageAlt are language-NEUTRAL + English-only-for-now respectively (alt folds into the translate pipeline later). `_label` = the English name the user gave for this category (reference only; not stored). Importer upserts by `type` (idempotent). Source: user-supplied URLs (2026-05-29). ALT TEXT: the user gave explicit alt for the first 3; the rest follow that same 'image from <event>' pattern (agent-composed, flagged for review).",
	"categories": [
		{ "_label": "Indoor World Series", "type": "Indoor World Series", "imageUrl": "https://images.axlothecook.com/archery/achivements/world-indoor-series.jpg", "imageAlt": "image from Indoor World Series" },
		{ "_label": "World Field Championships", "type": "Svjetsko prvenstvo u terenskom streličarstvu", "imageUrl": "https://images.axlothecook.com/archery/achivements/world-field-champ.jpg", "imageAlt": "image from World Field Championships" },
		{ "_label": "World Youth Championships", "type": "Svjetsko juniorsko prvenstvo", "imageUrl": "https://images.axlothecook.com/archery/achivements/world-youth-champ.jpg", "imageAlt": "image from World Youth Championships" },
		{ "_label": "World Cup Stage", "type": "Svjetski kup", "imageUrl": "https://images.axlothecook.com/archery/achivements/world-cup.jpg", "imageAlt": "image from World Cup Stage" },
		{ "_label": "European Field Championships", "type": "Europsko prvenstvo u terenskom streličarstvu", "imageUrl": "https://images.axlothecook.com/archery/achivements/eu-field-champ.jpg", "imageAlt": "image from European Field Championships" },
		{ "_label": "European Indoor Championships", "type": "Europsko dvoransko prvenstvo", "imageUrl": "https://images.axlothecook.com/archery/achivements/eu-indoor-champ.jpg", "imageAlt": "image from European Indoor Championships" },
		{ "_label": "European Youth Championships", "type": "Europsko juniorsko prvenstvo", "imageUrl": "https://images.axlothecook.com/archery/achivements/eu-youth-champ.jpg", "imageAlt": "image from European Youth Championships" },
		{ "_label": "European Youth Cup", "type": "Europski kup za mlade", "imageUrl": "https://images.axlothecook.com/archery/achivements/eu-youth-cup.jpg", "imageAlt": "image from European Youth Cup" },
		{ "_label": "European Grand Prix", "type": "Europski Grand Prix", "imageUrl": "https://images.axlothecook.com/archery/achivements/eu-grand-pri.jpg", "imageAlt": "image from European Grand Prix" },
		{ "_label": "European Outdoor Championships", "type": "Europsko prvenstvo na otvorenom", "imageUrl": "https://images.axlothecook.com/archery/achivements/eu-outdoor-champ.jpg", "imageAlt": "image from European Outdoor Championships" },
		{ "_label": "CEC", "type": "Central European Cup", "imageUrl": "https://images.axlothecook.com/archery/achivements/cec-champ.jpg", "imageAlt": "image from Central European Cup" },
		{ "_label": "Conquest Cup", "type": "Conquest Cup", "imageUrl": "https://images.axlothecook.com/archery/img1/post-62-1.jpg", "imageAlt": "image from Conquest Cup" },
		{ "_label": "Croatian Championship", "type": "Prvenstvo Hrvatske", "imageUrl": "https://images.axlothecook.com/archery/achivements/domestic-champ.jpg", "imageAlt": "image from Croatian Championship" },
		{ "_label": "Croatian 3D Cup", "type": "Hrvatski kup u 3D streličarstvu", "imageUrl": "https://images.axlothecook.com/archery/achivements/domestic-3d-cup.jpg", "imageAlt": "image from Croatian 3D Cup" },
		{ "_label": "Cadet World Record", "type": "Svjetski kadetski rekord", "imageUrl": "https://images.axlothecook.com/archery/achivements/cadet-world-record.jpg", "imageAlt": "image from Cadet World Record" },
		{ "_label": "European Junior Record", "type": "Europski juniorski rekord", "imageUrl": "https://images.axlothecook.com/archery/achivements/eu-jr-record.jpg", "imageAlt": "image from European Junior Record" },
		{ "_label": "Croatian National Record", "type": "Državni rekord", "imageUrl": "https://images.axlothecook.com/archery/achivements/domestic-record.jpg", "imageAlt": "image from Croatian National Record" }
	]
}
