{
	"_comment": "Official Croatian Archery Federation (HSS) 2026 competition calendar — transcribed VERBATIM from the HSS PDF (Kalendar-natjecanja-2026, verzija 22, 12.5.2026) at archery.hr. This is the SOURCE data for event generation (path B = domestic, path A cross-ref). It is NOT imported directly as ClubEvents; the event importers select/transform rows from it. `country` is derived from `mjesto` (location): HR = Croatia (domestic, path B); else the ISO-ish code shown in the calendar's organizator column (international, path A). `domestic` = (country === 'HR'). `format` is the calendar's format column (WC/EC/IWS/EWC/EGP/EYC/WRE/GP/PH/Kup/H3DK or null). `cancelled` = the red 'otkazano' rows. Empty date-only rows in the PDF (free terms) are omitted. Ignores _-prefixed annotation fields.",
	"_sourcePdf": "https://www.archery.hr/wp-content/uploads/2026/05/Kalendar-natjecanja-2026__v.22-12.5.2026.pdf",
	"_columns": "datum | disciplina | naziv | wa star | format | mjesto | organizator (org column doubles as country code for international rows)",
	"events": [
		{ "date": "2026-01-16", "dateTo": "2026-01-18", "discipline": "WA 2x18", "name": "Indoor World Series", "waStar": false, "format": "IWS", "location": "Nîmes", "organizer": "FRA", "country": "FRA", "domestic": false },
		{ "date": "2026-01-25", "discipline": "WA 2x25+2x18", "name": "Sisačka zima 2026", "waStar": false, "format": null, "location": "Sisak", "organizer": "Sisak", "country": "HR", "domestic": true },
		{ "date": "2026-02-08", "discipline": "WA 2x18+OR", "name": "Sisak Open 2026", "waStar": true, "format": null, "location": "Sisak", "organizer": "Sisak", "country": "HR", "domestic": true },
		{ "date": "2026-02-13", "dateTo": "2026-02-15", "discipline": "WA 2x18", "name": "Indoor World Series", "waStar": false, "format": "IWS", "location": "Merida", "organizer": "MEX", "country": "MEX", "domestic": false },
		{ "date": "2026-02-14", "discipline": "2x18", "name": "Morčići 2026", "waStar": false, "format": null, "location": "Rijeka", "organizer": "Rijeka", "country": "HR", "domestic": true },
		{ "date": "2026-02-16", "dateTo": "2026-02-21", "discipline": "WA 2x18", "name": "European Indoor Championships", "waStar": false, "format": "EWC", "location": "Plovdiv", "organizer": "BUL", "country": "BUL", "domestic": false },
		{ "date": "2026-02-22", "discipline": "WA 2x18", "name": "12. dvoranski turnir SK Koros", "waStar": true, "format": null, "location": "Kutina", "organizer": "Koros", "country": "HR", "domestic": true },
		{ "date": "2026-03-01", "discipline": "WA 2x18", "name": "28. Sv. Sebastijan i 41. Prvenstvo grada Zagreba", "waStar": true, "format": null, "location": "Zagreb", "organizer": "PSK", "country": "HR", "domestic": true },
		{ "date": "2026-03-07", "dateTo": "2026-03-08", "discipline": "WA 2x18+OR", "name": "PRVENSTVO HRVATSKE - DVORANA", "waStar": true, "format": "PH", "location": "Rijeka", "organizer": "Rijeka", "country": "HR", "domestic": true },
		{ "date": "2026-03-27", "dateTo": "2026-03-29", "discipline": "WA 2x18", "name": "Indoor World Series Finale", "waStar": false, "format": "IWS", "location": "Las Vegas", "organizer": "USA", "country": "USA", "domestic": false },
		{ "date": "2026-03-29", "discipline": "WA 2x18+OR", "name": "PRVENSTVO HRVATSKE - U13 - U15", "waStar": false, "format": "PH", "location": "Varaždin", "organizer": "VSK", "country": "HR", "domestic": true },
		{ "date": "2026-04-07", "dateTo": "2026-04-12", "discipline": "WA 720", "name": "Hyundai World Cup Stage 1", "waStar": false, "format": "WC", "location": "Puebla", "organizer": "MEX", "country": "MEX", "domestic": false },
		{ "date": "2026-04-20", "dateTo": "2026-04-26", "discipline": "WA 720", "name": "European Grand Prix 1st Leg", "waStar": false, "format": "EGP", "location": "Antalya", "organizer": "TUR", "country": "TUR", "domestic": false },
		{ "date": "2026-04-25", "discipline": "WA 3D", "name": "Sjevernjaci 2026", "waStar": false, "format": "H3DK", "location": "Utiskani", "organizer": "Bjelovar", "country": "HR", "domestic": true },
		{ "date": "2026-04-26", "discipline": "WA 720", "name": "Veliki pehar Nikole Zrinskog", "waStar": false, "format": null, "location": "Čakovec", "organizer": "Katarina Zrinski", "country": "HR", "domestic": true, "cancelled": true },
		{ "date": "2026-04-26", "discipline": "WA 720", "name": "CEC 1st Leg", "waStar": false, "format": "Kup", "location": "Lendava", "organizer": "SLO", "country": "SLO", "domestic": false },
		{ "date": "2026-05-03", "discipline": "WA720+MIX TIM", "name": "WA720+MIX TIM Sesvete 2026", "waStar": true, "format": null, "location": "Božjakovina", "organizer": "Sesvete", "country": "HR", "domestic": true, "cancelled": true },
		{ "date": "2026-05-05", "dateTo": "2026-05-10", "discipline": "WA 720", "name": "Hyundai World Cup Stage 2", "waStar": false, "format": "WC", "location": "Shanghai", "organizer": "PRC", "country": "PRC", "domestic": false },
		{ "date": "2026-05-09", "discipline": "WA 720", "name": "CEC 2nd Leg", "waStar": false, "format": "Kup", "location": "Kikinda", "organizer": "SRB", "country": "SRB", "domestic": false },
		{ "date": "2026-05-16", "discipline": "WA 720", "name": "Kup mladih Samobor 2026", "waStar": false, "format": "Kup", "location": "Samobor", "organizer": "SSŽŽ", "country": "HR", "domestic": true },
		{ "date": "2026-05-17", "discipline": "WA 3D", "name": "3D Pila 2026", "waStar": false, "format": "H3DK", "location": "Pila", "organizer": "ZGSK", "country": "HR", "domestic": true },
		{ "date": "2026-05-18", "dateTo": "2026-05-24", "discipline": "WA 720", "name": "European Outdoor Championships", "waStar": false, "format": "EC", "location": "Antalya", "organizer": "TUR", "country": "TUR", "domestic": false },
		{ "date": "2026-05-24", "discipline": "WA 720", "name": "Varaždin Open", "waStar": false, "format": null, "location": "Varaždin", "organizer": "Cekin", "country": "HR", "domestic": true },
		{ "date": "2026-05-28", "dateTo": "2026-05-31", "discipline": "WA 720", "name": "Veronica's Cup 2026", "waStar": false, "format": "WRE", "location": "Kamnik", "organizer": "SLO", "country": "SLO", "domestic": false },
		{ "date": "2026-05-30", "discipline": "WA 3D", "name": "Brinje Reunion '26", "waStar": false, "format": null, "location": "Prokike", "organizer": "Brinje", "country": "HR", "domestic": true },
		{ "date": "2026-05-31", "discipline": "WA 720", "name": "Kup mladih - Dan državnosti - Rakitje 2026", "waStar": true, "format": "Kup", "location": "Rakitje", "organizer": "Tigar", "country": "HR", "domestic": true },
		{ "date": "2026-06-01", "dateTo": "2026-06-06", "discipline": "WA 720", "name": "European Youth Cup 1st Leg", "waStar": false, "format": "EYC", "location": "Ruse", "organizer": "BUL", "country": "BUL", "domestic": false },
		{ "date": "2026-06-03", "dateTo": "2026-06-07", "discipline": "WA 720", "name": "Conquest Cup 2026", "waStar": false, "format": "WRE", "location": "Istanbul", "organizer": "TUR", "country": "TUR", "domestic": false },
		{ "date": "2026-06-07", "discipline": "WA 720", "name": "Dan grada Siska 2026", "waStar": false, "format": null, "location": "Sisak", "organizer": "Sisak", "country": "HR", "domestic": true },
		{ "date": "2026-06-09", "dateTo": "2026-06-14", "discipline": "WA 720", "name": "Hyundai World Cup Stage 3", "waStar": false, "format": "Kup", "location": "Antalya", "organizer": "TUR", "country": "TUR", "domestic": false },
		{ "date": "2026-06-14", "discipline": "WA 720 + OR", "name": "PRVENSTVO HRVATSKE U13 - U15", "waStar": false, "format": "PH", "location": "Zagreb", "organizer": "ZGSK", "country": "HR", "domestic": true },
		{ "date": "2026-06-20", "discipline": "WA 720+OR", "name": "CEC 3rd Leg", "waStar": true, "format": "Kup", "location": "Novi Marof", "organizer": "CRO", "country": "HR", "domestic": true },
		{ "date": "2026-06-21", "discipline": "3D", "name": "Sava 3D Pokal - Vitezovi-S", "waStar": false, "format": "Kup", "location": "Divčibare", "organizer": "SRB", "country": "SRB", "domestic": false },
		{ "date": "2026-06-28", "discipline": "WA 3D", "name": "Joševica 2026", "waStar": false, "format": "H3DK", "location": "Glina", "organizer": "Glina", "country": "HR", "domestic": true },
		{ "date": "2026-07-04", "discipline": "WA 720", "name": "CEC 4th Leg", "waStar": false, "format": "Kup", "location": "Vinicne", "organizer": "SVK", "country": "SVK", "domestic": false },
		{ "date": "2026-07-07", "dateTo": "2026-07-12", "discipline": "WA 720", "name": "Hyundai World Cup Stage 4", "waStar": false, "format": "WC", "location": "Madrid", "organizer": "ESP", "country": "ESP", "domestic": false },
		{ "date": "2026-07-18", "discipline": "3D", "name": "Sava 3D Pokal - SK Bjelovar", "waStar": false, "format": "Kup", "location": "Utiskani", "organizer": "CRO", "country": "HR", "domestic": true },
		{ "date": "2026-07-20", "dateTo": "2026-07-26", "discipline": "WA 720", "name": "European Youth Championships", "waStar": false, "format": "EYC", "location": "Rim", "organizer": "ITA", "country": "ITA", "domestic": false },
		{ "date": "2026-08-02", "discipline": "WA 720", "name": "Oluja 2026", "waStar": false, "format": null, "location": "Sisak", "organizer": "Sisak", "country": "HR", "domestic": true },
		{ "date": "2026-08-08", "discipline": "WA 720", "name": "Kup mladih Gerovo 2026", "waStar": false, "format": "Kup", "location": "Gerovo", "organizer": "3D Croatia Prezid", "country": "HR", "domestic": true },
		{ "date": "2026-08-21", "dateTo": "2026-09-03", "discipline": null, "name": "Mediterranean Games", "waStar": false, "format": null, "location": "Taranto", "organizer": "ITA", "country": "ITA", "domestic": false },
		{ "date": "2026-08-23", "discipline": "WA 720", "name": "CEC 5th Leg", "waStar": false, "format": "Kup", "location": "Beč", "organizer": "AUT", "country": "AUT", "domestic": false },
		{ "date": "2026-08-23", "discipline": "3D", "name": "Sava 3D Pokal - DLL Potens", "waStar": false, "format": "Kup", "location": "Mokrice", "organizer": "SLO", "country": "SLO", "domestic": false },
		{ "date": "2026-08-29", "dateTo": "2026-08-30", "discipline": "WA 720 + OR", "name": "PRVENSTVO HRVATSKE", "waStar": true, "format": "PH", "location": "Varaždin", "organizer": "VSK", "country": "HR", "domestic": true },
		{ "date": "2026-09-06", "discipline": "FIELD 12+12", "name": "PRVENSTVO HRVATSKE U POLJSKOM STRELIČARSTVU", "waStar": false, "format": "PH", "location": "Macelj", "organizer": "ZGSK", "country": "HR", "domestic": true },
		{ "date": "2026-09-12", "dateTo": "2026-09-13", "discipline": "WA 720", "name": "CEC Finale", "waStar": false, "format": "Kup", "location": "Budimpešta", "organizer": "HUN", "country": "HUN", "domestic": false },
		{ "date": "2026-09-19", "discipline": "WA 3D", "name": "PRVENSTVO HRVATSKE - 3D", "waStar": false, "format": "PH,H3DK", "location": "Prokike", "organizer": "Brinje", "country": "HR", "domestic": true },
		{ "date": "2026-09-20", "discipline": "WA 720", "name": "Kup mladih - Maestral - Rakitje 2026", "waStar": true, "format": "Kup", "location": "Rakitje", "organizer": "Tigar", "country": "HR", "domestic": true },
		{ "date": "2026-09-24", "dateTo": "2026-10-04", "discipline": "Field & 3D", "name": "Field and 3D World Championships", "waStar": false, "format": "WC", "location": "Yankton", "organizer": "USA", "country": "USA", "domestic": false },
		{ "date": "2026-10-17", "dateTo": "2026-10-18", "discipline": "WA 2x18+OR", "name": "Samobor Grand Prix 2026", "waStar": true, "format": "GP", "location": "Samobor", "organizer": "Samobor", "country": "HR", "domestic": true },
		{ "date": "2026-10-25", "discipline": "WA 2x18", "name": "Dvoranski streličarski turnir WA 2x18", "waStar": true, "format": null, "location": "Kutina", "organizer": "Kutina", "country": "HR", "domestic": true },
		{ "date": "2026-10-31", "dateTo": "2026-11-13", "discipline": "WA 720", "name": "Youth Olympic Games", "waStar": false, "format": null, "location": "Dakar", "organizer": "SEN", "country": "SEN", "domestic": false },
		{ "date": "2026-11-13", "dateTo": "2026-11-15", "discipline": "3x18", "name": "Kings of Archery - JVD Open", "waStar": false, "format": "IWS", "location": "Eindhoven", "organizer": "NL", "country": "NL", "domestic": false },
		{ "date": "2026-11-14", "discipline": "WA 2x18+OR", "name": "Martinjski turnir", "waStar": true, "format": null, "location": "Ljubešćica", "organizer": "Grebengradski streličari", "country": "HR", "domestic": true },
		{ "date": "2026-11-20", "dateTo": "2026-11-22", "discipline": "WA 2x18", "name": "GT Open", "waStar": false, "format": "IWS", "location": "Luxembourg", "organizer": "LUX", "country": "LUX", "domestic": false },
		{ "date": "2026-11-29", "discipline": "WA 2x25+2x18", "name": "Varaždin Open 2x25 + 2x18m", "waStar": true, "format": null, "location": "Varaždin", "organizer": "VSK", "country": "HR", "domestic": true },
		{ "date": "2026-12-06", "discipline": "WA 2x18", "name": "Sveti Nikola 2026", "waStar": false, "format": null, "location": "Sisak", "organizer": "Sisak", "country": "HR", "domestic": true },
		{ "date": "2026-12-20", "discipline": "WA 2x18", "name": "XXXIII Božićni turnir", "waStar": false, "format": null, "location": "Varaždin", "organizer": "Cekin", "country": "HR", "domestic": true }
	]
}
